{
    "type": "minecraft:crafting_shaped",
    "category": "equipment",
    "key": {
      "#": {
      "tag": "minecraft:planks"
      },
      "X": {
        "item": "minecraft:iron_ingot"
      }
    },
    "pattern": [
      "X#X",
      "XXX",
      " X "
    ],
    "result": {
      "count": 1,
      "id": "minecraft:shield",
      "components": {
                    "minecraft:item_name":"{\"text\":\"铁盾\"}",
                    "minecraft:max_damage": 672,
                    "minecraft:attribute_modifiers": {
                        "show_in_tooltip":false,
                        "modifiers":[
                            {
                                "id":"mainhand",
                                "type":"minecraft:generic.armor",
                                "amount":3.0,
                                "slot":"mainhand",
                                "operation":"add_value"
                            },
                            {
                                "id":"mainhand",
                                "type":"minecraft:generic.armor_toughness",
                                "amount":1.0,
                                "slot":"mainhand",
                                "operation":"add_value"
                            },
                            {
                                "id":"mainhand",
                                "type":"minecraft:generic.movement_speed",
                                "amount":-0.2,
                                "slot":"mainhand",
                                "operation":"add_multiplied_base"
                            },
                            {
                              "id":"offhand",
                              "type":"minecraft:generic.armor",
                              "amount":3.0,
                              "slot":"offhand",
                              "operation":"add_value"
                            },
                            {
                                "id":"offhand",
                                "type":"minecraft:generic.armor_toughness",
                                "amount":1.0,
                                "slot":"offhand",
                                "operation":"add_value"
                            },
                            {
                                "id":"offhand",
                                "type":"minecraft:generic.movement_speed",
                                "amount":-0.2,
                                "slot":"offhand",
                                "operation":"add_multiplied_base"
                            }
                        ]
                      },
                      "minecraft:lore": [
                        "[{\"text\":\"\",\"color\":\"gray\",\"italic\":false}]",
                        "[{\"text\":\"手持时：\",\"color\":\"gray\",\"italic\":false}]",
                        "[{\"text\":\"+3 护甲值\",\"color\":\"blue\",\"italic\":false}]",
                        "[{\"text\":\"+1 盔甲韧性\",\"color\":\"blue\",\"italic\":false}]",
                        "[{\"text\":\"-20% 速度\",\"color\":\"red\",\"italic\":false}]"
                      ]
                    }
                }
            }